mindaudio/__init__.py
mindaudio/version.py
mindaudio/data/__init__.py
mindaudio/data/aishell.py
mindaudio/data/augment.py
mindaudio/data/features.py
mindaudio/data/filters.py
mindaudio/data/io.py
mindaudio/data/librispeech.py
mindaudio/data/processing.py
mindaudio/data/spectrum.py
mindaudio/data/voxceleb.py
mindaudio/loss/AdditiveAngularMargin.py
mindaudio/loss/__init__.py
mindaudio/loss/ctc_loss.py
mindaudio/loss/label_smoothing_loss.py
mindaudio/loss/loss_scale.py
mindaudio/loss/separation_loss.py
mindaudio/metric/__init__.py
mindaudio/metric/eer.py
mindaudio/metric/snr.py
mindaudio/metric/wer.py
mindaudio/models/__init__.py
mindaudio/models/conformer.py
mindaudio/models/conv_tasnet.py
mindaudio/models/deepspeech2.py
mindaudio/models/ecapatdnn.py
mindaudio/models/tasnet.py
mindaudio/models/decoders/__init__.py
mindaudio/models/decoders/decoder_factory.py
mindaudio/models/decoders/greedydecoder.py
mindaudio/models/fastspeech2/__init__.py
mindaudio/models/fastspeech2/fastspeech2_v190.py
mindaudio/models/fastspeech2/loss.py
mindaudio/models/fastspeech2/utils.py
mindaudio/models/fastspeech2/variance_adapter.py
mindaudio/models/layers/__init__.py
mindaudio/models/layers/attention.py
mindaudio/models/layers/cmvn.py
mindaudio/models/layers/conv1d.py
mindaudio/models/layers/conv2d.py
mindaudio/models/layers/convolution.py
mindaudio/models/layers/dense.py
mindaudio/models/layers/embedding.py
mindaudio/models/layers/glu.py
mindaudio/models/layers/layernorm.py
mindaudio/models/layers/positionwise_feed_forward.py
mindaudio/models/layers/softmax_cross_entropy.py
mindaudio/models/layers/subsampling.py
mindaudio/models/layers/swish.py
mindaudio/models/transformer/__init__.py
mindaudio/models/transformer/constants.py
mindaudio/models/transformer/layers.py
mindaudio/models/transformer/models.py
mindaudio/models/transformer/positional_encoding.py
mindaudio/models/transformer/score_function.py
mindaudio/models/transformer/sublayers.py
mindaudio/models/wavegrad/__init__.py
mindaudio-0.3.0.dist-info/LICENSE
mindaudio-0.3.0.dist-info/METADATA
mindaudio-0.3.0.dist-info/WHEEL
mindaudio-0.3.0.dist-info/top_level.txt
mindaudio-0.3.0.dist-info/RECORD
