Metadata-Version: 2.1
Name: mindaudio
Version: 0.3.0
Summary: A toolbox of audio models and algorithms based on MindSpore.
Home-page: https://github.com/mindspore-lab/mindaudio
Author: MindSpore Lab
Author-email: mindspore-lab@example.com
License: Apache Software License 2.0
Project-URL: Sources, https://github.com/mindspore-lab/mindaudio
Project-URL: Issue Tracker, https://github.com/mindspore-lab/mindaudio/issues
Classifier: Development Status :: 3 - Alpha
Classifier: License :: OSI Approved :: Apache Software License
Classifier: Operating System :: POSIX :: Linux
Classifier: Programming Language :: Python :: 3
Classifier: Programming Language :: Python :: 3.8
Classifier: Programming Language :: Python :: 3.9
Classifier: Topic :: Scientific/Engineering :: Artificial Intelligence
Requires-Python: >=3.8
License-File: LICENSE
Requires-Dist: numpy
Requires-Dist: pyyaml
Requires-Dist: tqdm
Requires-Dist: scipy
Requires-Dist: sentencepiece
